swarm_tf/__init__.py
swarm_tf/common/__init__.py
swarm_tf/common/scripts/install-docker-ce.sh
swarm_tf/managers/__init__.py
swarm_tf/managers/scripts/get-swarm-join-tokens.sh
swarm_tf/managers/scripts/provision-first-manager.sh
swarm_tf/managers/scripts/provision-manager.sh
swarm_tf/managers/scripts/certs/coreos.sh
swarm_tf/managers/scripts/certs/default.sh
swarm_tf/workers/__init__.py
swarm_tf/workers/scripts/attach_volume.sh
swarm_tf/workers/scripts/join.sh
swarm_tf/workers/scripts/nfs.sh
swarm_tf-0.2.4.data/scripts/connect_to_manager
swarm_tf-0.2.4.data/scripts/terrascript
swarm_tf-0.2.4.dist-info/METADATA
swarm_tf-0.2.4.dist-info/WHEEL
swarm_tf-0.2.4.dist-info/dependency_links.txt
swarm_tf-0.2.4.dist-info/top_level.txt
swarm_tf-0.2.4.dist-info/RECORD
