Metadata-Version: 2.1
Name: swarm-tf
Version: 0.2.4
Summary: Create a Swarm Cluster on Digital Ocean using Terraform Wrapped by Python
Home-page: https://github.com/byjg/swarm_tf
Author: Joao Gilberto Magalhaes
Author-email: joao@byjg.com.br
License: MIT
Platform: UNKNOWN
Classifier: Programming Language :: Python :: 3
Classifier: License :: OSI Approved :: MIT License
Classifier: Operating System :: OS Independent
Requires-Dist: terraobject (==0.0.1)
Requires-Dist: terrascript (==0.6.0)
